zaggregator/__init__.py
zaggregator/__main__.py
zaggregator/client.py
zaggregator/daemon.py
zaggregator/procbundle.py
zaggregator/sqlite.py
zaggregator/utils.py
zaggregator/tests/__init__.py
zaggregator/tests/__main__.py
zaggregator/tests/run_asyncio.py
zaggregator/tests/test_procbundle.py
zaggregator/tests/test_proctable.py
zaggregator/tests/test_sqlite.py
zaggregator/tests/test_utils.py
zaggregator-0.0.1.dist-info/METADATA
zaggregator-0.0.1.dist-info/RECORD
zaggregator-0.0.1.dist-info/WHEEL
zaggregator-0.0.1.dist-info/top_level.txt
